Metadata-Version: 1.0
Name: jickle
Version: 0.1.2
Summary: JSON pickle
Home-page: http://github.com/ronfe/jickle
Author: ronfe
Author-email: hongfei@guanghe.tv
License: MIT
Platform: UNKNOWN
